scarcc/__init__.py
scarcc/data_analysis/__init__.py
scarcc/data_analysis/biomass/__init__.py
scarcc/data_analysis/biomass/_pathway_summary.py
scarcc/data_analysis/biomass/growth_summary.py
scarcc/data_analysis/biomass/plot_growth_curve.py
scarcc/data_analysis/drug_combination_response/__init__.py
scarcc/data_analysis/drug_combination_response/classification.py
scarcc/data_analysis/flux/__init__.py
scarcc/data_analysis/flux/carbon_allocation.py
scarcc/data_analysis/flux/flux_correction.py
scarcc/data_analysis/flux/flux_ratio_analysis.py
scarcc/data_analysis/flux/flux_snapshot.py
scarcc/data_analysis/growth/__init__.py
scarcc/data_analysis/growth/_pathway_summary.py
scarcc/data_analysis/growth/growth_rate.py
scarcc/data_analysis/growth/growth_summary.py
scarcc/data_analysis/growth/plot_growth_curve.py
scarcc/data_analysis/plot/__init__.py
scarcc/data_analysis/plot/heatmap.py
scarcc/data_analysis/plot/kde.py
scarcc/data_analysis/plot/legend.py
scarcc/data_analysis/plot/scatter.py
scarcc/preparation/__init__.py
scarcc/preparation/find_directory.py
scarcc/preparation/metabolic_model/__init__.py
scarcc/preparation/metabolic_model/basic_model.py
scarcc/preparation/metabolic_model/core/__init__.py
scarcc/preparation/metabolic_model/core/component.py
scarcc/preparation/metabolic_model/core/flux_weighting.py
scarcc/preparation/metabolic_model/core/medium.py
scarcc/preparation/perturbation/__init__.py
scarcc/preparation/perturbation/alpha_finder/__init__.py
scarcc/preparation/perturbation/alpha_finder/alpha_finder.py
scarcc/preparation/perturbation/alpha_finder/checkerboard.py
scarcc/preparation/perturbation/alpha_finder/coculture.py
scarcc/preparation/perturbation/alpha_finder/monoculture.py
scarcc/preparation/perturbation/function/__init__.py
scarcc/preparation/perturbation/function/iter_species.py
scarcc/preparation/perturbation/function/stoichiometry_scaling.py
scarcc/preparation/target_gene/__init__.py
scarcc/preparation/target_gene/gene_format_handler.py
scarcc-0.1.10.dist-info/LICENSE
scarcc-0.1.10.dist-info/METADATA
scarcc-0.1.10.dist-info/WHEEL
scarcc-0.1.10.dist-info/top_level.txt
scarcc-0.1.10.dist-info/RECORD
