Metadata-Version: 2.1
Name: scarcc
Version: 0.1.10
Home-page: https://github.com/TFwongw/scarccpy
Author: Thomas Wong
Author-email: wong0755@umn.edu
Requires-Python: >=3.10
License-File: LICENSE
Requires-Dist: pandas <2.3
Requires-Dist: matplotlib
Requires-Dist: seaborn >0.11
Requires-Dist: cobra
Requires-Dist: cometspy
Requires-Dist: scipy
Provides-Extra: docs
Requires-Dist: sphinx ; extra == 'docs'
Requires-Dist: sphinx-rtd-theme ; extra == 'docs'
